<theme>						
	<variant name="list-video">					
		<aspectRatio name="1:1">				
			<view name="gamelist">			
				<video name="game-system-video">		
					<pos>0.665388888888889 0.4845</pos>	
					<size>0.202111111111111 0.136555555555556</size>	
				</video>		
			</view>			
		</aspectRatio>				
		<aspectRatio name="5:4">				
			<view name="gamelist">			
				<video name="game-system-video">		
					<pos>0.665388888888889 0.48075</pos>	
					<size>0.202111111111111 0.170444444444444</size>	
				</video>		
			</view>			
		</aspectRatio>				
		<aspectRatio name="4:3">				
			<view name="gamelist">			
				<video name="game-system-video">		
					<pos>0.665388888888889 0.4795</pos>	
					<size>0.202111111111111 0.181740740740741</size>	
				</video>		
			</view>			
		</aspectRatio>				
		<aspectRatio name="3:2">				
			<view name="gamelist">			
				<video name="game-system-video">		
					<pos>0.665388888888889 0.477</pos>	
					<size>0.202111111111111 0.204333333333333</size>	
				</video>		
			</view>			
		</aspectRatio>				
		<aspectRatio name="16:10">				
			<view name="gamelist">			
				<video name="game-system-video">		
					<pos>0.665446759259259 0.47675</pos>	
					<size>0.191636574074074 0.206592592592593</size>	
				</video>		
			</view>			
		</aspectRatio>				
		<aspectRatio name="16:9">				
			<view name="gamelist">			
				<video name="game-system-video">		
					<pos>0.665552083333333 0.47675</pos>	
					<size>0.172572916666667 0.206592592592593</size>	
				</video>		
			</view>			
		</aspectRatio>				
		<aspectRatio name="19.5:9">				
			<view name="gamelist">			
				<video name="game-system-video">		
					<pos>0.6657222222222221 0.47675</pos>	
					<size>0.141777777777778 0.206592592592593</size>	
				</video>		
			</view>			
		</aspectRatio>				
		<aspectRatio name="21:9">				
			<view name="gamelist">			
				<video name="game-system-video">		
					<pos>0.665777777777778 0.47675</pos>	
					<size>0.131722222222222 0.206592592592593</size>	
				</video>		
			</view>			
		</aspectRatio>				
   </variant>						
</theme>