<theme>						
	<variant name="list-video">					
		<aspectRatio name="1:1">				
			<view name="gamelist">			
				<video name="game-system-video">		
					<pos>0.668166666666667 0.419333333333333</pos>	
					<size>0.193222222222222 0.194777777777778</size>	
				</video>		
			</view>			
		</aspectRatio>				
		<aspectRatio name="5:4">				
			<view name="gamelist">			
				<video name="game-system-video">		
					<pos>0.668166666666667 0.399541666666667</pos>	
					<size>0.193222222222222 0.242972222222222</size>	
				</video>		
			</view>			
		</aspectRatio>				
		<aspectRatio name="4:3">				
			<view name="gamelist">			
				<video name="game-system-video">		
					<pos>0.668166666666667 0.392944444444444</pos>	
					<size>0.193222222222222 0.259037037037037</size>	
				</video>		
			</view>			
		</aspectRatio>				
		<aspectRatio name="3:2">				
			<view name="gamelist">			
				<video name="game-system-video">		
					<pos>0.668166666666667 0.37975</pos>	
					<size>0.193222222222222 0.291166666666667</size>	
				</video>		
			</view>			
		</aspectRatio>				
		<aspectRatio name="16:10">				
			<view name="gamelist">			
				<video name="game-system-video">		
					<pos>0.6680798611111111 0.378430555555556</pos>	
					<size>0.183210648148148 0.29437962962963</size>	
				</video>		
			</view>			
		</aspectRatio>				
		<aspectRatio name="16:9">				
			<view name="gamelist">			
				<video name="game-system-video">		
					<pos>0.6679218750000001 0.378430555555556</pos>	
					<size>0.164989583333333 0.29437962962963</size>	
				</video>		
			</view>			
		</aspectRatio>				
		<aspectRatio name="19.5:9">				
			<view name="gamelist">			
				<video name="game-system-video">		
					<pos>0.6676666666666671 0.378430555555556</pos>	
					<size>0.135555555555556 0.29437962962963</size>	
				</video>		
			</view>			
		</aspectRatio>				
		<aspectRatio name="21:9">				
			<view name="gamelist">			
				<video name="game-system-video">		
					<pos>0.6675833333333331 0.378430555555556</pos>	
					<size>0.125944444444444 0.29437962962963</size>	
				</video>		
			</view>			
		</aspectRatio>				
   </variant>						
</theme>